Workbook

Sheet Executive Summary
A1: UK Physical-Product Niche Research
A2: Supplier-first decision pack • UK market desk research • 6 August 2026 • exact keyword volumes intentionally left for tool export
A4: Decision | J4: Top opportunities after supplier-gate screen
A5: Best first lane: rainwater and drought-resilience systems, provided a manufacturer will protect channel economics and support design/installation. Best ecommerce-native lane: owned or contract-manufactured performance acoustic room kits. Sensory-room packages are the strongest supplier-led B2B alternative. Freediving should not launch as a general UK catalogue: the supplier gate fails today.
A10: What changed because of Access Ropes
A11: Supplier defensibility is a hard gate, not a weighted nice-to-have. Reject any opportunity where the supplier/manufacturer can quote the same buyer directly, run permanent DTC discounts, vary wholesale pricing without notice, or leave you with one source and no protected SKU. A high raw demand score cannot rescue a failed supplier gate.
A16: Immediate recommendation
A17: Step | C17: Output
A18: 1 | B18: Run supplier diligence in parallel | C18: 8 rainwater suppliers/manufacturers, 3 acoustic contract makers, Sense Sensory, CompoCloset + 2 alternatives.
A19: 2 | B19: Do not buy inventory yet | C19: Get written price notice, DTC parity, warranty, stock and territory/unique-SKU terms first.
A20: 3 | B20: Validate two offers | C20: Rainwater sizing/quote tool and performance acoustic room-plan/kit tool; £1.5k–£3k test budget per lane. | J20: Opportunity | K20: Score
A21: 4 | B21: Keep freediving as an option | C21: Only move if an exclusive/protected premium supplier agrees terms; then test club-led fit/demo demand. | J21: ='Opportunity Scorecard'!B7 | K21: ='Opportunity Scorecard'!N7
J22: ='Opportunity Scorecard'!B8 | K22: ='Opportunity Scorecard'!N8
J23: ='Opportunity Scorecard'!B9 | K23: ='Opportunity Scorecard'!N9
J24: ='Opportunity Scorecard'!B10 | K24: ='Opportunity Scorecard'!N10
J25: ='Opportunity Scorecard'!B11 | K25: ='Opportunity Scorecard'!N11
J26: ='Opportunity Scorecard'!B12 | K26: ='Opportunity Scorecard'!N12

Sheet Opportunity Scorecard
A1: Opportunity Scorecard
A2: Scores are formula-weighted from Weights & Method. Supplier score below 3 automatically rejects the niche.
A4: Use the score to focus diligence—not to skip it. Yellow supplier cells are the most consequential assumption. Evidence IDs map to Sources.
A6: Rank | B6: Opportunity | C6: Product / AOV thesis | D6: Search tier* | E6: Supplier defensibility | F6: Demand evidence | G6: Competition gap | H6: AOV and margin potential | I6: SEO and content fit | J6: Repeat / cross-sell | K6: Trend durability | L6: Operational ease | M6: Founder fit | N6: Weighted score | O6: Supplier gate | P6: Decision | Q6: Confidence | R6: Why it may work | S6: Main risk | T6: Evidence IDs
A7: 1 | B7: Rainwater & drought-resilience systems | C7: £1.5k–£7k domestic/SME kits; quote-led commercial systems £15k–£40k | D7: Medium, rising | E7: 4 | F7: 4.4 | G7: 3.8 | H7: 4.8 | I7: 5 | J7: 3 | K7: 5 | L7: 2 | M7: 4 | N7: =SUM(E7*'Weights & Method'!$B$6,F7*'Weights & Method'!$B$7,G7*'Weights & Method'!$B$8,H7*'Weights & Method'!$B$9,I7*'Weights & Method'!$B$10,J7*'Weights & Method'!$B$11,K7*'Weights & Method'!$B$12,L7*'Weights & Method'!$B$13,M7*'Weights & Method'!$B$14)/5 | O7: =IF(E7<3,"FAIL",IF(E7<4,"CONDITIONAL","PASS")) | P7: =IF(E7<3,"Reject: supplier gate",IF(E7<4,"Supplier DD",IF(N7>=75,"Priority test",IF(N7>=68,"Supplier DD",IF(N7>=60,"Watchlist","Reject"))))) | Q7: High | R7: Exceptional 2026 demand signal plus long-term water deficit; calculator-led sale suits your digital skillset. | S7: Bulky delivery, design responsibility, installation and standards; many manufacturers also sell direct. | T7: S14 S15 S16 S17 S18 S73
A8: 2 | B8: Performance acoustic room kits | C8: £600–£2.5k studio, listening-room, podcast and office kits; contract-made/owned range | D8: High | E8: 4.5 | F8: 4.2 | G8: 3.5 | H8: 4 | I8: 5 | J8: 2.5 | K8: 4 | L8: 3 | M8: 4.5 | N8: =SUM(E8*'Weights & Method'!$B$6,F8*'Weights & Method'!$B$7,G8*'Weights & Method'!$B$8,H8*'Weights & Method'!$B$9,I8*'Weights & Method'!$B$10,J8*'Weights & Method'!$B$11,K8*'Weights & Method'!$B$12,L8*'Weights & Method'!$B$13,M8*'Weights & Method'!$B$14)/5 | O8: =IF(E8<3,"FAIL",IF(E8<4,"CONDITIONAL","PASS")) | P8: =IF(E8<3,"Reject: supplier gate",IF(E8<4,"Supplier DD",IF(N8>=75,"Priority test",IF(N8>=68,"Supplier DD",IF(N8>=60,"Watchlist","Reject"))))) | Q8: High | R8: Strong content surface and custom-kit margin; UK makers/reseller routes exist. Differentiate by measured performance, not décor. | S8: Generic slat panels are commoditised; fire/acoustic test evidence and bulky shipping are essential. | T8: S08 S09 S10 S11 S12 S13
A9: 3 | B9: Sensory-room packages | C9: £3k–£15k+ school, care and home packages with design and installation partners | D9: Medium | E9: 4.5 | F9: 4 | G9: 3.2 | H9: 5 | I9: 4 | J9: 3 | K9: 4.5 | L9: 2 | M9: 3 | N9: =SUM(E9*'Weights & Method'!$B$6,F9*'Weights & Method'!$B$7,G9*'Weights & Method'!$B$8,H9*'Weights & Method'!$B$9,I9*'Weights & Method'!$B$10,J9*'Weights & Method'!$B$11,K9*'Weights & Method'!$B$12,L9*'Weights & Method'!$B$13,M9*'Weights & Method'!$B$14)/5 | O9: =IF(E9<3,"FAIL",IF(E9<4,"CONDITIONAL","PASS")) | P9: =IF(E9<3,"Reject: supplier gate",IF(E9<4,"Supplier DD",IF(N9>=75,"Priority test",IF(N9>=68,"Supplier DD",IF(N9>=60,"Watchlist","Reject"))))) | Q9: High | R9: UK manufacturer explicitly recruits resellers; funded inclusion programme and public procurement routes support demand. | S9: Consultative/ethical sale, safeguarding and public procurement; expertise and installation matter more than Shopify alone. | T9: S19 S20 S21 S22 S23
A10: 4 | B10: Separating & composting toilet systems | C10: £300–£1k boat, campervan, cabin and garden-room installation kits plus consumables | D10: Medium | E10: 4 | F10: 3.5 | G10: 3.5 | H10: 4 | I10: 5 | J10: 4 | K10: 4.3 | L10: 3.5 | M10: 4 | N10: =SUM(E10*'Weights & Method'!$B$6,F10*'Weights & Method'!$B$7,G10*'Weights & Method'!$B$8,H10*'Weights & Method'!$B$9,I10*'Weights & Method'!$B$10,J10*'Weights & Method'!$B$11,K10*'Weights & Method'!$B$12,L10*'Weights & Method'!$B$13,M10*'Weights & Method'!$B$14)/5 | O10: =IF(E10<3,"FAIL",IF(E10<4,"CONDITIONAL","PASS")) | P10: =IF(E10<3,"Reject: supplier gate",IF(E10<4,"Supplier DD",IF(N10>=75,"Priority test",IF(N10>=68,"Supplier DD",IF(N10>=60,"Watchlist","Reject"))))) | Q10: High | R10: Explicit wholesale route, product trend named by a major camping body, clear application-led SEO and repeat consumables. | S10: Some brands sell direct/affiliate at low commission; odour, fitting and support failures damage trust quickly. | T10: S24 S25 S26 S27 S28
A11: 5 | B11: Pond-health & filtration systems | C11: £850–£3k koi/large-pond filtration, pumps, UV and treatment bundles | D11: High, seasonal | E11: 3.5 | F11: 4 | G11: 3 | H11: 4 | I11: 5 | J11: 5 | K11: 3.8 | L11: 2.5 | M11: 4 | N11: =SUM(E11*'Weights & Method'!$B$6,F11*'Weights & Method'!$B$7,G11*'Weights & Method'!$B$8,H11*'Weights & Method'!$B$9,I11*'Weights & Method'!$B$10,J11*'Weights & Method'!$B$11,K11*'Weights & Method'!$B$12,L11*'Weights & Method'!$B$13,M11*'Weights & Method'!$B$14)/5 | O11: =IF(E11<3,"FAIL",IF(E11<4,"CONDITIONAL","PASS")) | P11: =IF(E11<3,"Reject: supplier gate",IF(E11<4,"Supplier DD",IF(N11>=75,"Priority test",IF(N11>=68,"Supplier DD",IF(N11>=60,"Watchlist","Reject"))))) | Q11: High | R11: High-value upper end, recurring media/treatments and sizing content; established dealer/wholesale channels. | S11: Mature specialists, seasonality, bulky wet products and technical sizing/warranty support. | T11: S29 S30 S31 S32 S33
A12: 6 | B12: Microcement installer systems | C12: Professional system kits, training and recurring installer consumables | D12: High | E12: 3 | F12: 4 | G12: 3 | H12: 4 | I12: 4.5 | J12: 5 | K12: 4 | L12: 2.5 | M12: 4 | N12: =SUM(E12*'Weights & Method'!$B$6,F12*'Weights & Method'!$B$7,G12*'Weights & Method'!$B$8,H12*'Weights & Method'!$B$9,I12*'Weights & Method'!$B$10,J12*'Weights & Method'!$B$11,K12*'Weights & Method'!$B$12,L12*'Weights & Method'!$B$13,M12*'Weights & Method'!$B$14)/5 | O12: =IF(E12<3,"FAIL",IF(E12<4,"CONDITIONAL","PASS")) | P12: =IF(E12<3,"Reject: supplier gate",IF(E12<4,"Supplier DD",IF(N12>=75,"Priority test",IF(N12>=68,"Supplier DD",IF(N12>=60,"Watchlist","Reject"))))) | Q12: Medium | R12: Growing design-led surface category with excellent repeat consumables and certification-led community model. | S12: Leading systems restrict purchase to trained installers; technical failure and waterproofing claims carry liability. | T12: S46 S47
A13: 7 | B13: Golf simulator components & rooms | C13: £1.5k–£25k+ DIY-to-installed simulator packages, mats, screens and monitors | D13: High | E13: 3 | F13: 4 | G13: 2.5 | H13: 5 | I13: 4.5 | J13: 3.5 | K13: 4.3 | L13: 1.5 | M13: 3.5 | N13: =SUM(E13*'Weights & Method'!$B$6,F13*'Weights & Method'!$B$7,G13*'Weights & Method'!$B$8,H13*'Weights & Method'!$B$9,I13*'Weights & Method'!$B$10,J13*'Weights & Method'!$B$11,K13*'Weights & Method'!$B$12,L13*'Weights & Method'!$B$13,M13*'Weights & Method'!$B$14)/5 | O13: =IF(E13<3,"FAIL",IF(E13<4,"CONDITIONAL","PASS")) | P13: =IF(E13<3,"Reject: supplier gate",IF(E13<4,"Supplier DD",IF(N13>=75,"Priority test",IF(N13>=68,"Supplier DD",IF(N13>=60,"Watchlist","Reject"))))) | Q13: Medium | R13: Large AOV and clear comparison/search journey; manufacturer partner programmes exist. | S13: Crowded installers, fast hardware cycles and software subscriptions; check conflict with your golf client. | T13: S48 S49 S75 S76
A14: 8 | B14: Electric outboards | C14: £1k–£8k electric motors and battery/charging packages with regional demo/service | D14: Medium | E14: 3.5 | F14: 3.2 | G14: 2.8 | H14: 5 | I14: 4 | J14: 3 | K14: 4.5 | L14: 1.5 | M14: 3 | N14: =SUM(E14*'Weights & Method'!$B$6,F14*'Weights & Method'!$B$7,G14*'Weights & Method'!$B$8,H14*'Weights & Method'!$B$9,I14*'Weights & Method'!$B$10,J14*'Weights & Method'!$B$11,K14*'Weights & Method'!$B$12,L14*'Weights & Method'!$B$13,M14*'Weights & Method'!$B$14)/5 | O14: =IF(E14<3,"FAIL",IF(E14<4,"CONDITIONAL","PASS")) | P14: =IF(E14<3,"Reject: supplier gate",IF(E14<4,"Supplier DD",IF(N14>=75,"Priority test",IF(N14>=68,"Supplier DD",IF(N14>=60,"Watchlist","Reject"))))) | Q14: High | R14: Dealer programmes, premium AOV and structural electrification trend. | S14: Battery freight, demo/service expectations and established south-coast dealer networks make pure ecommerce weak. | T14: S38 S39 S40 S41
A15: 9 | B15: Home pottery studio systems | C15: £1.5k–£5k wheel/kiln/starter packages plus clay, glazes and firing accessories | D15: Medium | E15: 3 | F15: 3.5 | G15: 2.5 | H15: 5 | I15: 4.5 | J15: 5 | K15: 4 | L15: 1.5 | M15: 3 | N15: =SUM(E15*'Weights & Method'!$B$6,F15*'Weights & Method'!$B$7,G15*'Weights & Method'!$B$8,H15*'Weights & Method'!$B$9,I15*'Weights & Method'!$B$10,J15*'Weights & Method'!$B$11,K15*'Weights & Method'!$B$12,L15*'Weights & Method'!$B$13,M15*'Weights & Method'!$B$14)/5 | O15: =IF(E15<3,"FAIL",IF(E15<4,"CONDITIONAL","PASS")) | P15: =IF(E15<3,"Reject: supplier gate",IF(E15<4,"Supplier DD",IF(N15>=75,"Priority test",IF(N15>=68,"Supplier DD",IF(N15>=60,"Watchlist","Reject"))))) | Q15: High | R15: Very high AOV with excellent consumables and education/community potential. | S15: Entrenched technical dealers, price matching, long lead times, electrical/install support and heavy freight. | T15: S42 S43 S44 S45
A16: 10 | B16: Building diagnostic kits | C16: £1k–£3.5k thermal camera + moisture/borescope + training/report-template bundles | D16: High | E16: 3 | F16: 3.8 | G16: 2.8 | H16: 4 | I16: 5 | J16: 2.5 | K16: 4 | L16: 3 | M16: 4 | N16: =SUM(E16*'Weights & Method'!$B$6,F16*'Weights & Method'!$B$7,G16*'Weights & Method'!$B$8,H16*'Weights & Method'!$B$9,I16*'Weights & Method'!$B$10,J16*'Weights & Method'!$B$11,K16*'Weights & Method'!$B$12,L16*'Weights & Method'!$B$13,M16*'Weights & Method'!$B$14)/5 | O16: =IF(E16<3,"FAIL",IF(E16<4,"CONDITIONAL","PASS")) | P16: =IF(E16<3,"Reject: supplier gate",IF(E16<4,"Supplier DD",IF(N16>=75,"Priority test",IF(N16>=68,"Supplier DD",IF(N16>=60,"Watchlist","Reject"))))) | Q16: High | R16: Excellent B2B comparison/content opportunity and strong AOV; retrofit/EPC change keeps diagnostics relevant. | S16: Master distributors are strong, low-end cameras are commoditised, and training/calibration support is expected. | T16: S34 S35 S36 S37
A17: 11 | B17: Sewing & embroidery machines | C17: £500–£10k machines with training, servicing and recurring thread/stabiliser/accessories | D17: Very high | E17: 3 | F17: 4.2 | G17: 2 | H17: 5 | I17: 4 | J17: 5 | K17: 4 | L17: 1.5 | M17: 3 | N17: =SUM(E17*'Weights & Method'!$B$6,F17*'Weights & Method'!$B$7,G17*'Weights & Method'!$B$8,H17*'Weights & Method'!$B$9,I17*'Weights & Method'!$B$10,J17*'Weights & Method'!$B$11,K17*'Weights & Method'!$B$12,L17*'Weights & Method'!$B$13,M17*'Weights & Method'!$B$14)/5 | O17: =IF(E17<3,"FAIL",IF(E17<4,"CONDITIONAL","PASS")) | P17: =IF(E17<3,"Reject: supplier gate",IF(E17<4,"Supplier DD",IF(N17>=75,"Priority test",IF(N17>=68,"Supplier DD",IF(N17>=60,"Watchlist","Reject"))))) | Q17: High | R17: Current UK participation signal, large AOV ladder and powerful recurring consumables. | S17: Mature showroom/service incumbents, finance and trade-in expectations; difficult to enter without repair capability. | T17: S63 S64
A18: 12 | B18: Commercial/home Pilates reformers | C18: £1.2k–£3.5k reformers; studio packs, delivery/setup and accessories | D18: Very high | E18: 2.5 | F18: 4.8 | G18: 2 | H18: 5 | I18: 4.5 | J18: 3 | K18: 4.5 | L18: 2 | M18: 3 | N18: =SUM(E18*'Weights & Method'!$B$6,F18*'Weights & Method'!$B$7,G18*'Weights & Method'!$B$8,H18*'Weights & Method'!$B$9,I18*'Weights & Method'!$B$10,J18*'Weights & Method'!$B$11,K18*'Weights & Method'!$B$12,L18*'Weights & Method'!$B$13,M18*'Weights & Method'!$B$14)/5 | O18: =IF(E18<3,"FAIL",IF(E18<4,"CONDITIONAL","PASS")) | P18: =IF(E18<3,"Reject: supplier gate",IF(E18<4,"Supplier DD",IF(N18>=75,"Priority test",IF(N18>=68,"Supplier DD",IF(N18>=60,"Watchlist","Reject"))))) | Q18: Medium | R18: Exceptional current demand and AOV; OEM/private-label supply is available. | S18: Price compression from mass retail, bulky returns, safety/warranty and intense DTC/social competition. | T18: S50 S51
... A31: 25 | B31: Home freeze dryers | C31: £2.5k–£5.7k preservation equipment plus bags, oil, trays and maintenance | D31: Niche | E31: 1.5 | F31: 2 | G31: 3 | H31: 5 | I31: 4 | J31: 4 | K31: 3 | L31: 1.5 | M31: 3 | N31: =SUM(E31*'Weights & Method'!$B$6,F31*'Weights & Method'!$B$7,G31*'Weights & Method'!$B$8,H31*'Weights & Method'!$B$9,I31*'Weights & Method'!$B$10,J31*'Weights & Method'!$B$11,K31*'Weights & Method'!$B$12,L31*'Weights & Method'!$B$13,M31*'Weights & Method'!$B$14)/5 | O31: =IF(E31<3,"FAIL",IF(E31<4,"CONDITIONAL","PASS")) | P31: =IF(E31<3,"Reject: supplier gate",IF(E31<4,"Supplier DD",IF(N31>=75,"Priority test",IF(N31>=68,"Supplier DD",IF(N31>=60,"Watchlist","Reject"))))) | Q31: High | R31: Very high AOV and consumables, with visible UK supply gap/lead times. | S31: Single-brand dependency, direct global pricing, refrigeration service and extremely narrow UK demand. | T31: S54 S80

Sheet Weights & Method
A1: Weights & Method
A2: Editable weights • all scores are 1–5 • supplier defensibility is also a hard gate
A4: Weighted score
A5: Criterion | B5: Weight | C5: What is being scored | D5: 1 / weak | E5: 3 / acceptable | F5: 5 / strong | G5: Notes
A6: Supplier defensibility | B6: 25 | C6: Manufacturer cannot routinely undercut; written terms, protected SKUs/territory or own-brand path | D6: Direct conflict / unilateral terms | E6: Basic wholesale relationship | F6: Exclusive, private-label, JV or multi-source structure
A7: Demand evidence | B7: 15 | C7: UK buyer problem, category breadth and current demand signals | D7: Weak / anecdotal | E7: Stable niche | F7: Strong, broad or institutionally funded
A8: Competition gap | B8: 15 | C8: Room to win without being the cheapest identical SKU | D8: Dominated by DTC, Amazon or entrenched specialists | E8: Some whitespace | F8: Clear underserved buyer/use case
A9: AOV and margin potential | B9: 15 | C9: Ability to reach useful gross profit per order | D9: Low AOV / thin margin | E9: £250–£750 with workable margin | F9: £1k+ or strong own-brand margin
A10: SEO and content fit | B10: 10 | C10: Depth of problem-led search journeys and comparison content | D10: Few valuable queries | E10: Several buying journeys | F10: Rich calculator, comparison and specification content
A11: Repeat / cross-sell | B11: 5 | C11: Consumables, service, upgrades or adjacent products | D11: One-off only | E11: Accessories / occasional repeat | F11: Consumables or recurring service
A12: Trend durability | B12: 5 | C12: Structural rather than short-lived demand | D12: Fad / policy cliff | E12: Stable | F12: Long-term structural tailwind
A13: Operational ease | B13: 5 | C13: Shipping, returns, installation, warranty and support burden | D13: Heavy service / installation | E13: Manageable complexity | F13: Simple fulfilment and low returns
A14: Founder fit | B14: 5 | C14: Digital acquisition, ecommerce, technical content and credible access | D14: Needs deep missing expertise | E14: Learnable | F14: Strong fit / authentic community access
A15: Total | B15: =SUM(B6:B14)
A17: Hard gates and decision logic
A18: Supplier gate | B18: PASS | C18: Supplier score ≥4.0/5 and no hard-stop flag
A19: Supplier gate | B19: CONDITIONAL | C19: Supplier score 3.0–3.9; written terms or second source not yet proven
A20: Supplier gate | B20: FAIL | C20: Supplier score <3.0 or direct-quote/DTC/price-protection hard stop
A21: Priority test | B21: Score ≥75 | C21: Only if supplier gate is PASS; CONDITIONAL suppliers remain in diligence
A22: Supplier DD | B22: Score 68–74.9 | C22: Commercially attractive but channel/support structure needs proof
A23: Watchlist | B23: Score 60–67.9 | C23: Do not allocate material time before priority lanes are resolved
A25: Search-demand limitation
A26: No exact UK monthly search volumes are fabricated in this pack. The search tier is a directional desk-research judgement based on category breadth, search-result depth and demand evidence. Paste Semrush, Ahrefs or Keyword Planner volumes into the yellow cells on Keyword Validation; exact volumes, CPC and keyword difficulty should be a Phase-2 check on the top two lanes, not a false-precision input across 25 ideas.

Sheet Supplier Gate
A1: Supplier Gate
A2: Score two real suppliers side by side before inventory, ads or a catalogue build
A4: Supplier scorecard
A5: Criterion | B5: Why it matters | C5: Weight | D5: Supplier A (0–2) | E5: Supplier B (0–2) | F5: Required written evidence | G5: Hard stop if 0?
A6: Wholesale price fixed / notice | B6: Prevents Southern Ropes-style quote erosion | C6: 2 | F6: 12-month price list or ≥90-day notice | G6: Yes
A7: Core-SKU gross margin | B7: Funds acquisition, support and returns | C7: 2 | F7: ≥35% landed GM at normal street price | G7: Yes
A8: DTC price parity | B8: Stops the manufacturer becoming your cheapest competitor | C8: 2 | F8: Policy covering coupons, bundles and marketplaces | G8: Yes
A9: No direct end-customer quoting | B9: Protects leads you create | C9: 2 | F9: Lead registration / non-circumvention clause | G9: Yes
A10: Protected SKU / territory / segment | B10: Makes comparison harder and rewards demand creation | C10: 2 | F10: Exclusive SKU, geography or named vertical | G10: No
A11: Second-source or own-brand path | B11: Reduces single-supplier fragility | C11: 2 | F11: Alternative BOM, contract manufacturing or exit rights | G11: No
A12: Stock allocation and feed | B12: Prevents ads selling unavailable product | C12: 1 | F12: Stock feed, allocation and back-order SLA | G12: No
A13: Dispatch / delivery SLA | B13: Protects service promise | C13: 1 | F13: Written dispatch times and peak-season plan | G13: No
A14: Warranty / RMA ownership | B14: Avoids margin being consumed by faults | C14: 2 | F14: Who pays freight, turnaround and replacement SLA | G14: Yes
A15: Certification and insurance | B15: Required for safe, defendable claims | C15: 2 | F15: Test reports, declarations, product-liability cover | G15: Yes
A16: Credit terms improve with volume | B16: Reduces working-capital strain | C16: 1 | F16: Deposit / net terms / credit ladder | G16: No
A17: Data, samples and training | B17: Enables superior product pages and advice | C17: 1 | F17: Assets, demo units, training and claim approval | G17: No
... A20: Reference checks | B20: Tests whether promises survive growth | C20: 1 | F20: Two current reseller references | G20: No
A22: Weighted gate score / 5 | D22: =SUMPRODUCT(C6:C20,D6:D20)/(SUM(C6:C20)*2)*5 | E22: =SUMPRODUCT(C6:C20,E6:E20)/(SUM(C6:C20)*2)*5
A23: Result | D23: =IF(OR(D6=0,D7=0,D8=0,D9=0,D14=0,D15=0),"FAIL",IF(D22>=4,"PASS",IF(D22>=3,"CONDITIONAL","FAIL"))) | E23: =IF(OR(E6=0,E7=0,E8=0,E9=0,E14=0,E15=0),"FAIL",IF(E22>=4,"PASS",IF(E22>=3,"CONDITIONAL","FAIL")))
A25: Automatic hard stops
A26: 1 | B26: Supplier/manufacturer can quote your registered lead directly or transfer it to another dealer.
A27: 2 | B27: Normal DTC/promotional price leaves less than 30% landed gross margin—or price protection is verbal only.
A28: 3 | B28: Price changes can take effect immediately, with no quote validity or inventory protection.
A29: 4 | B29: You rely on one source and have neither exclusivity, unique SKUs, private label nor an exit/second-source plan.
A30: 5 | B30: Warranty, safety certification or liability ownership is unclear.

Sheet Shortlist Deep Dives
A1: Shortlist Deep Dives
A2: The product thesis must be differentiated at supplier/BOM level—not just by better marketing
A5: Rank | B5: Opportunity | C5: Buyer | D5: Offer wedge | E5: Indicative AOV | F5: Required supplier structure | G5: Why now | H5: Primary risk | I5: First validation action | J5: Decision
A6: 1 | B6: Rainwater & drought-resilience systems | C6: Homeowners, rural properties, small businesses, farms and developers | D6: Packaged roof-to-use system: tank + filter + pump + controls + drip irrigation; calculator and installer handoff | E6: £1.5k–£7k domestic; £15k–£40k commercial | F6: Exclusive/approved manufacturer deal or JV; unique bundled BOM; at least two tank/component sources | G6: 2026 drought + structural deficit; high-value problem-led search | H6: Design/install burden; direct-selling manufacturers | I6: Contact 8 UK makers/distributors; require written price/channel terms before any landing page | J6: Priority 1
A7: 2 | B7: Performance acoustic room kits | C7: Home studios, podcasters, listening rooms, creators and smaller offices | D7: Performance-tested room kits by room/use case; custom finish; remote plan service | E7: £600–£2.5k | F7: Contract manufacture/owned SKU; performance/fire documentation; no identical-brand price comparison | G7: Rich search/comparison surface; manageable ecommerce; strong margin potential | H7: Generic slat-panel commoditisation and bulky freight | I7: Quote three UK panel makers for an exclusive kit specification and tested construction | J7: Priority 2
A8: 3 | B8: Sensory-room packages | C8: Schools, local authorities, care settings, charities and higher-income home buyers | D8: Three fixed packages plus paid design, installation partner and refurbishment service | E8: £3k–£15k+ | F8: Sense Sensory reseller route plus framework-ready supplier relationship | G8: Explicit reseller invitation and funded inclusion/procurement tailwind | H8: Expertise, procurement cycles, safeguarding and installation | I8: Supplier call + 10 SENCO/OT interviews; test quote-led landing page, not broad paid shopping | J8: Priority 3 (B2B)
A9: 4 | B9: Separating & composting toilet systems | C9: Campervan/boat converters, garden rooms, cabins and off-grid buyers | D9: Application-specific install kits, vent/electrical options, consumable replenishment | E9: £300–£1k | F9: Wholesale programme + second UK/EU maker; own installation kits and documentation | G9: Named 2026 trend, active wholesale route and recurring consumables | H9: Brand DTC/affiliate conflict; support/reputation sensitivity | I9: Ask CompoCloset and two makers for wholesale, warranty and no-undercut terms | J9: Priority 4
A10: 5 | B10: Pond-health & filtration systems | C10: Koi and large-pond owners with clarity/water-quality problems | D10: Pond-size calculator, filtration/pump/UV bundles and scheduled media/treatment replenishment | E10: £850–£3k | F10: Dealer/wholesale brands plus own bundle SKUs; avoid identical standalone hero SKU | G10: High product depth, repeat revenue and urgent problem searches | H10: Seasonal, mature specialists and technical sizing | I10: Model three pond sizes and price-protect bundles with two wholesalers | J10: Supplier DD
A11: 6 | B11: Building diagnostic kits | C11: Surveyors, retrofit coordinators, electricians, landlords and maintenance teams | D11: Use-case kits combining camera, moisture meter, borescope, case, training and report templates | E11: £1k–£3.5k | F11: Authorised second-tier manufacturer + owned training/templates; two camera brands | G11: Strong B2B intent and comparison content; professional AOV | H11: Master distributors, calibration and low-end commoditisation | I11: Interview 12 surveyors; seek vertical-kit rights from 3 brands before ad test | J11: Supplier DD
A12: — | B12: Premium freediving equipment | C12: Committed club divers, instructors and spearfishers | D12: Appointment/demo-led premium fit studio: fins + wetsuit + computer; club partnerships | E12: £400–£1.2k | F12: Only launch with protected UK/segment rights, 12-month pricing, DTC parity and second line | G12: Authentic fit, active community and premium products | H12: Small TAM; EU price leader; existing UK specialists; brand DTC | I12: Do 10 club/instructor interviews and 8 supplier calls first. No catalogue build until gate passes | J12: No-go until supplier solved

Sheet Freediving Deep Dive
A1: Freediving Deep Dive
A2: Conclusion: attractive founder/category fit, but not a launchable general store until the supplier structure changes
A4: Verdict
A5: NO-GO as a broad UK catalogue today. The UK has an active but small community and premium products can reach £400–£675+; however, Diveinn states UK prices already include VAT and duties, major brands sell direct, and UK specialists already stock premium lines. The viable version is an exclusive/protected premium fit-and-demo business, not 'the same EU catalogue held in Britain'.
A10: Evidence at a glance
A11: Dimension | B11: Evidence | C11: Implication
A12: Community | B12: BFA governs the sport; NoTanx reports 500 UK pool sessions/year and multiple branches. | C12: Real enthusiasts and partnership nodes, but this does not prove a large national TAM. S02 S03
A13: Premium AOV | B13: Freediving London lists Alchemy models roughly £405–£675. | C13: Fins can support meaningful gross profit if wholesale protection exists. S04
A14: EU friction | B14: Diveinn says displayed UK price is final and VAT/duties are included. | C14: Fast UK delivery alone is a convenience, not a defensible price moat. S01
A15: UK competition | B15: Mike's Dive Store, Spearfishing UK and Freediving London already cover the category. | C15: A general catalogue enters an existing specialist set. S04 S06 S07
A16: Manufacturer power | B16: Premium brands operate direct ecommerce/content. | C16: Identical-SKU reselling risks the same squeeze experienced in ropes. S05
A18: What would make it investable
A19: Requirement | B19: Minimum | C19: Why | D19: Evidence to obtain | E19: Fail result
A20: Protected line | B20: Exclusive UK, protected channel/segment or genuinely unique SKU | C20: Prevents direct price comparison | D20: Signed distribution agreement | E20: Do not launch
A21: Price protection | B21: 12-month wholesale price or ≥90-day notice; quotes honoured | C21: Prevents Access Ropes repeat | D21: Price schedule + quote validity | E21: Do not launch
A22: DTC parity | B22: Brand checkout/promos never undercut your landed target price | C22: Keeps paid/SEO demand economically yours | D22: Written parity/MAP-equivalent terms | E22: Do not launch
A23: Margin | B23: ≥35% landed GM on protected hero products; ≥£150 GP/order | C23: Funds fit advice, returns and acquisition | D23: Landed-cost model with real discounts | E23: Do not launch
A24: Resilience | B24: Two complementary premium lines or own-brand accessory path | C24: Reduces single-brand dependence | D24: Second supplier / contract sample | E24: Stay pilot-only
A25: Warranty | B25: UK turnaround and clear fault/fit return rules | C25: Carbon fins/wetsuits need trust | D25: RMA SLA and freight ownership | E25: Do not stock
A27: Viable offer design if the gate passes
A28: Layer | B28: Offer | C28: Indicative basket | D28: Moat | E28: Commercial role
A29: Entry | B29: Club demo / fit session and digital fit questionnaire | C29: Lead / refundable fitting fee | D29: Community + expertise | E29: Qualify serious buyers
A30: Core | B30: Carbon fin + foot pocket + fitting package | C30: £450–£700 | D30: Protected line + demo | E30: Hero gross profit
A31: Premium | B31: Fins + made-to-measure wetsuit + computer | C31: £900–£1,500 | D31: Fit, bundled advice and local aftercare | E31: Raises AOV
A32: Repeat | B32: Lanyards, weights, masks, bags, care and replacement parts | C32: £25–£200 | D32: Owned bundles / content | E32: Retention and cross-sell
A33: Channel | B33: Instructor/club partner programme | C33: Revenue share or demo credits | D33: Trusted distribution | E33: Lower CAC
A35: Four-week proof test (only after supplier conversations)
A36: Customer discovery | B36: 10 instructor/club interviews + 20 serious divers | C36: ≥60% name a fit/availability/aftercare pain worth paying a UK premium for
A37: Supplier discovery | B37: 8 premium/emerging brand conversations | C37: At least one passes every hard gate above
A38: Demand capture | B38: Three product/fit pages and club referrals; no unfulfillable sales | C38: 30 qualified UK leads and 5 refundable fitting/deposit intents
A39: Economics | B39: Quote real delivery, fees, returns and support | C39: ≥35% landed GM, ≥15% contribution, ≥£150 gross profit/order
A40: Decision | B40: Review at day 28 | C40: Proceed only if supplier gate passes and ≥60% forecast revenue is from protected SKUs

Sheet Keyword Validation
A1: Keyword Validation
A2: Yellow cells are intentionally blank. Paste current UK monthly volume/CPC/KD from Semrush, Ahrefs or Keyword Planner.
A4: Directional tiers are screening judgements—not substitute keyword volumes. Use exact data only on the top two supplier-safe ideas after supplier terms are credible.
A6: Opportunity | B6: Directional tier | C6: Keyword 1 | D6: UK vol 1 | E6: Keyword 2 | F6: UK vol 2 | G6: Keyword 3 | H6: UK vol 3 | I6: Keyword 4 | J6: UK vol 4 | K6: Basket volume | L6: Primary CPC £ | M6: Primary KD | N6: Data status
A7: Rainwater & drought-resilience systems | B7: Medium, rising | C7: rainwater harvesting system | D7: 1300 | E7: rainwater harvesting system UK | F7: 60 | G7: rainwater tank | H7: 450 | I7: rainwater recycling system | J7: 150 | K7: 1960 | L7: 0.28 | M7: 3 | N7: Ahrefs GB Aug 2026 (partial; n/a = not pulled)
A8: Performance acoustic room kits | B8: High | C8: acoustic panels | D8: 25000 | E8: acoustic treatment | F8: 400 | G8: acoustic room kit | H8: 0 | I8: studio acoustic panels | J8: 150 | K8: 25550 | L8: 0.87 | M8: 3 | N8: Ahrefs GB Aug 2026 (partial; n/a = not pulled)
A9: Sensory-room packages | B9: Medium | C9: sensory room equipment | D9: 1000 | E9: sensory room package | F9: 10 | G9: sensory room for school | H9: 0 | I9: sensory room design | J9: n/a | K9: 1010 | L9: 0.47 | M9: 2 | N9: Ahrefs GB Aug 2026 (partial; n/a = not pulled)
A10: Separating & composting toilet systems | B10: Medium | C10: composting toilet | D10: 1900 | E10: separating toilet | F10: 150 | G10: waterless toilet | H10: 250 | I10: campervan composting toilet | J10: 100 | K10: 2400 | L10: 0.16 | M10: 3 | N10: Ahrefs GB Aug 2026 (partial; n/a = not pulled)
A11: Pond-health & filtration systems | B11: High, seasonal | C11: pond filter | D11: 2600 | E11: koi pond filter | F11: 350 | G11: pond filtration system | H11: 150 | I11: drum filter pond | J11: 10 | K11: 3110 | L11: 0.16 | M11: 2 | N11: Ahrefs GB Aug 2026 (partial; n/a = not pulled)
A12: Microcement installer systems | B12: High | C12: microcement | D12: 7000 | E12: microcement kit | F12: 200 | G12: microcement bathroom | H12: 4300 | I12: microcement supplier | J12: n/a | K12: 11500 | L12: 0.55 | M12: 3 | N12: Ahrefs GB Aug 2026 (partial; n/a = not pulled)
A13: Golf simulator components & rooms | B13: High | C13: golf simulator | D13: 13000 | E13: golf simulator UK | F13: 350 | G13: golf launch monitor | H13: 1900 | I13: golf simulator enclosure | J13: n/a | K13: 15250 | L13: 0.63 | M13: 7 | N13: Ahrefs GB Aug 2026 (partial; n/a = not pulled)
A14: Electric outboards | B14: Medium | C14: electric outboard motor | D14: 2200 | E14: electric outboard UK | F14: n/a | G14: Torqeedo outboard | H14: 100 | I14: ePropulsion outboard | J14: n/a | K14: 2300 | L14: 0.24 | M14: 3 | N14: Ahrefs GB Aug 2026 (partial; n/a = not pulled)
A15: Home pottery studio systems | B15: Medium | C15: pottery kiln | D15: 1400 | E15: pottery wheel | F15: 4300 | G15: electric kiln UK | H15: n/a | I15: home pottery studio | J15: n/a | K15: 5700 | L15: 0.08 | M15: 0 | N15: Ahrefs GB Aug 2026 (partial; n/a = not pulled)
A16: Building diagnostic kits | B16: High | C16: thermal imaging camera | D16: 8800 | E16: thermal camera building inspection | F16: n/a | G16: FLIR thermal camera | H16: n/a | I16: damp survey equipment | J16: n/a | K16: 8800 | L16: 0.32 | M16: 5 | N16: Ahrefs GB Aug 2026 (partial; n/a = not pulled)
A17: Sewing & embroidery machines | B17: Very high | C17: sewing machine | D17: 37000 | E17: embroidery machine | F17: n/a | G17: computerised sewing machine | H17: n/a | I17: industrial embroidery machine | J17: n/a | K17: 37000 | L17: 0.16 | M17: 31 | N17: Ahrefs GB Aug 2026 (partial; n/a = not pulled)
A18: Commercial/home Pilates reformers | B18: Very high | C18: Pilates reformer | D18: 22000 | E18: reformer Pilates machine | F18: n/a | G18: commercial Pilates reformer | H18: n/a | I18: foldable reformer | J18: n/a | K18: 22000 | L18: 0.47 | M18: 26 | N18: Ahrefs GB Aug 2026 (partial; n/a = not pulled)
A19: Cold-plunge & contrast therapy systems | B19: High | C19: cold plunge | D19: 3600 | E19: ice bath | F19: 19000 | G19: cold plunge chiller | H19: n/a | I19: home sauna and ice bath | J19: n/a | K19: 22600 | L19: 0.55 | M19: 55 | N19: Ahrefs GB Aug 2026 (partial; n/a = not pulled)
A20: Garden irrigation systems | B20: High, seasonal | C20: garden irrigation system | D20: 1800 | E20: drip irrigation kit | F20: 150 | G20: automatic watering system | H20: n/a | I20: garden irrigation kit | J20: n/a | K20: 1950 | L20: 0.24 | M20: 5 | N20: Ahrefs GB Aug 2026 (partial; n/a = not pulled)
A21: Robotic lawn mowers | B21: Very high | C21: robot lawn mower | D21: 17000 | E21: robot mower | F21: n/a | G21: wireless robot mower | H21: n/a | I21: robot mower installation | J21: n/a | K21: 17000 | L21: 0.2 | M21: 0 | N21: Ahrefs GB Aug 2026 (partial; n/a = not pulled)
A22: Premium freediving equipment | B22: Niche | C22: freediving equipment | D22: 90 | E22: freediving fins | F22: 200 | G22: carbon freediving fins | H22: n/a | I22: freediving wetsuit | J22: n/a | K22: 290 | L22: 0.16 | M22: 0 | N22: Ahrefs GB Aug 2026 (partial; n/a = not pulled)
A23: Workshop dust extraction | B23: High | C23: dust extractor | D23: 6200 | E23: workshop dust extraction | F23: n/a | G23: woodworking dust extractor | H23: n/a | I23: dust extraction system | J23: n/a | K23: 6200 | L23: 0.24 | M23: 0 | N23: Ahrefs GB Aug 2026 (partial; n/a = not pulled)
A24: EVSE installer test kits | B24: Niche B2B | C24: EVSE tester | D24: n/a | E24: EV charger tester | F24: n/a | G24: EV testing equipment | H24: n/a | I24: EV charger commissioning kit | J24: n/a | K24: =IF(COUNT(D24,F24,H24,J24)=0,"",SUM(D24,F24,H24,J24)) | N24: =IF(K24="","Not populated","Loaded")
A25: Home coffee roasting systems | B25: Niche | C25: home coffee roaster | D25: 250 | E25: coffee roasting machine | F25: n/a | G25: Aillio Bullet | H25: n/a | I25: green coffee beans UK | J25: n/a | K25: 250 | L25: 0.28 | M25: 5 | N25: Ahrefs GB Aug 2026 (partial; n/a = not pulled)
A26: Metal detecting systems | B26: High | C26: metal detector | D26: 14000 | E26: metal detector UK | F26: n/a | G26: Minelab detector | H26: n/a | I26: metal detecting accessories | J26: n/a | K26: 14000 | L26: 0.28 | M26: 34 | N26: Ahrefs GB Aug 2026 (partial; n/a = not pulled)
A27: Beekeeping extraction equipment | B27: Medium | C27: honey extractor | D27: 250 | E27: beekeeping equipment | F27: n/a | G27: electric honey extractor | H27: n/a | I27: beekeeping starter kit | J27: n/a | K27: 250 | L27: 0.12 | M27: 0 | N27: Ahrefs GB Aug 2026 (partial; n/a = not pulled)
A28: Robotic pool cleaners | B28: Medium, seasonal | C28: robot pool cleaner | D28: 40 | E28: Dolphin pool cleaner | F28: n/a | G28: automatic pool cleaner | H28: n/a | I28: cordless pool robot | J28: n/a | K28: 40 | L28: 0.36 | M28: 0 | N28: Ahrefs GB Aug 2026 (partial; n/a = not pulled)
A29: Ecology & bat-survey equipment | B29: Niche B2B | C29: bat detector | D29: 1800 | E29: bat survey equipment | F29: n/a | G29: Wildlife Acoustics detector | H29: n/a | I29: ecology survey equipment | J29: n/a | K29: 1800 | L29: 0.16 | M29: 0 | N29: Ahrefs GB Aug 2026 (partial; n/a = not pulled)
A30: Dog mobility equipment | B30: High | C30: dog wheelchair | D30: 1400 | E30: dog mobility harness | F30: n/a | G30: dog ramp | H30: n/a | I30: disabled dog equipment | J30: n/a | K30: 1400 | L30: 0.12 | M30: 5 | N30: Ahrefs GB Aug 2026 (partial; n/a = not pulled)
A31: Home freeze dryers | B31: Niche | C31: freeze dryer UK | D31: 700 | E31: home freeze dryer | F31: n/a | G31: Harvest Right freeze dryer | H31: n/a | I31: food freeze dryer | J31: n/a | K31: 700 | L31: 0.16 | M31: 0 | N31: Ahrefs GB Aug 2026 (partial; n/a = not pulled)

Sheet Unit Economics
A1: Unit Economics
A2: Editable launch hypotheses—not observed supplier quotes. Yellow inputs must be replaced with real landed costs and CAC tests.
A4: Contribution = AOV × gross margin − outbound freight − payment fees − return/defect reserve − CAC. It excludes salaries, storage and installation labour; use it as a first commercial filter only.
A6: Opportunity | B6: AOV £ | C6: Target GM % | D6: Outbound freight £ | E6: Payment fee % | F6: Return/defect reserve % | G6: CAC £ | H6: Contribution £ | I6: Contribution % | J6: Model note
A7: Rainwater & drought-resilience systems | B7: 3500 | C7: 0.32 | D7: 180 | E7: 0.018 | F7: 0.01 | G7: 220 | H7: =ROUND(B7*C7-D7-B7*E7-B7*F7-G7,0) | I7: =H7/B7 | J7: Dropship / installer-partner hypothesis
A8: Performance acoustic room kits | B8: 950 | C8: 0.5 | D8: 55 | E8: 0.018 | F8: 0.03 | G8: 80 | H8: =ROUND(B8*C8-D8-B8*E8-B8*F8-G8,0) | I8: =H8/B8 | J8: Owned/contract-made range hypothesis
A9: Sensory-room packages | B9: 6000 | C9: 0.35 | D9: 550 | E9: 0.006 | F9: 0.01 | G9: 500 | H9: =ROUND(B9*C9-D9-B9*E9-B9*F9-G9,0) | I9: =H9/B9 | J9: Invoice-led institutional sale
A10: Separating & composting toilet systems | B10: 650 | C10: 0.38 | D10: 25 | E10: 0.018 | F10: 0.03 | G10: 65 | H10: =ROUND(B10*C10-D10-B10*E10-B10*F10-G10,0) | I10: =H10/B10 | J10: Kit + consumables hypothesis
A11: Pond-health & filtration systems | B11: 1100 | C11: 0.35 | D11: 45 | E11: 0.018 | F11: 0.03 | G11: 100 | H11: =ROUND(B11*C11-D11-B11*E11-B11*F11-G11,0) | I11: =H11/B11 | J11: High-end filter bundle
A12: Building diagnostic kits | B12: 1800 | C12: 0.28 | D12: 15 | E12: 0.018 | F12: 0.02 | G12: 140 | H12: =ROUND(B12*C12-D12-B12*E12-B12*F12-G12,0) | I12: =H12/B12 | J12: Authorised dealer + own bundle
A13: Premium freediving equipment | B13: 450 | C13: 0.35 | D13: 10 | E13: 0.018 | F13: 0.07 | G13: 50 | H13: =ROUND(B13*C13-D13-B13*E13-B13*F13-G13,0) | I13: =H13/B13 | J13: Shows fragility without protected margin
A17: Commercial go/no-go thresholds
A18: Landed gross margin | B18: ≥35% | C18: Lower only for invoiced/high-AOV B2B with proven low acquisition and service cost
A19: Contribution after CAC | B19: ≥15% of revenue | C19: And ≥£150/order for advice-heavy products
A20: Protected revenue | B20: ≥60% | C20: Share of forecast sales from exclusive, private-label, unique-bundle or registered-lead products
A21: Single supplier exposure | B21: ≤50% by month 12 | C21: Or explicit exclusivity/price protection plus viable exit stock terms
A22: Price notice | B22: ≥90 days | C22: Existing quotes and owned inventory protected

Sheet 90-Day Validation
A1: 90-Day Validation
A2: Spend follows evidence: supplier terms → customer proof → landing-page economics → inventory
A4: Phase | B4: Timing | C4: Rainwater lane | D4: Acoustic lane | E4: Freediving option | F4: Exit criterion | G4: Owner | H4: Status
A5: 1. Supplier reality | B5: Days 1–14 | C5: 8 maker/distributor calls; collect terms, BOM, freight, certifications and install support | D5: 3 UK contract-maker quotes; define owned construction, performance/fire evidence and freight | E5: 8 premium-brand calls; exclusivity/parity only | F5: At least one supplier scores PASS and a second is plausible | H5: Not started
A6: 2. Buyer language | B6: Days 8–24 | C6: 15 homeowners/rural/SME + 5 installers; map triggers, sizing and objections | D6: 15 creators/studios/offices; map room, appearance, result and budget | E6: 10 instructors/clubs + 20 committed divers | F6: ≥60% report a painful, current problem and credible spend | H6: Not started
A7: 3. Offer prototype | B7: Days 20–38 | C7: Sizing calculator + 3 packages + installer handoff | D7: Remote room-plan flow + 3 use-case kits + samples | E7: Fit/demo page only if supplier PASS | F7: 10 qualified quote/plan requests per lane | H7: Not started
A8: 4. Acquisition test | B8: Days 35–65 | C8: Search/content + £1.5k–£3k controlled media | D8: Search/content + £1.5k–£3k controlled media | E8: Club referrals; minimal paid spend | F8: Qualified-lead economics imply ≥15% contribution at target close rate | H8: Not started
A9: 5. Supply pilot | B9: Days 55–80 | C9: 5–10 fulfilled/dropshipped or assisted installs | D9: 10–20 contract-made/low-MOQ kits | E9: 5 fitting/deposit intents; no stock before terms | F9: Delivery, damage, return and support burden fit model | H9: Not started
A10: 6. Investment decision | B10: Days 81–90 | C10: Choose supplier/BOM, working capital and launch geography | D10: Choose owned range, MOQ and content plan | E10: Proceed/park | F10: All hard gates pass; economics and service are reproducible | H10: Not started
A12: Decision checkpoints
A13: Day 14 | B13: No supplier PASS | C13: Stop the lane; do not compensate with a prettier website.
A14: Day 38 | B14: Weak buyer proof | C14: Reframe the use case once; then park if demand remains vague.
A15: Day 65 | B15: Contribution <15% | C15: Raise AOV/margin, reduce service/CAC, or stop.
A16: Day 80 | B16: Supplier terms changed | C16: Re-score from zero; the relationship is the product.
A17: Day 90 | B17: One lane passes all gates | C17: Commit inventory and a 6-month content/acquisition roadmap only then.

Sheet Sources
A1: Sources
A2: Public web research reviewed 6 August 2026 • source type and confidence are shown to avoid false precision
A4: ID | B4: Theme | C4: Source | D4: Source type | E4: Evidence used | F4: Confidence | G4: Accessed | H4: URL
A5: S01 | B5: Freediving | C5: Diveinn | D5: Retailer/help | E5: UK prices shown are final; VAT and duties included, weakening import-friction as a moat. | F5: High | G5: 46240 | H5: https://www.tradeinn.com/diveinn/en/help/st
A6: S02 | B6: Freediving | C6: British Freediving Association | D6: Governing body | E6: UK governing body and affiliated-club network; membership and active community evidence. | F6: High | G6: 46240 | H6: https://britishfreediving.org/
A7: S03 | B7: Freediving | C7: NoTanx | D7: Club | E7: Reports 500 pool sessions/year, UK holidays, international trips and branches in multiple cities. | F7: High | G7: 46240 | H7: https://www.notanx.com/about-us
A8: S04 | B8: Freediving | C8: Freediving London | D8: UK retailer | E8: Premium Alchemy carbon fins listed roughly £405–£675, showing premium AOV and existing UK specialist supply. | F8: High | G8: 46240 | H8: https://freedivinglondon.co.uk/product-category/alchemy/alchemy-fins/
A9: S05 | B9: Freediving | C9: Alchemy | D9: Manufacturer DTC | E9: Premium manufacturer has its own direct ecommerce/content presence. | F9: High | G9: 46240 | H9: https://alchemy.gr/
A10: S06 | B10: Freediving | C10: Mike's Dive Store | D10: UK competitor | E10: Large UK dive retailer with freediving/scuba breadth. | F10: High | G10: 46240 | H10: https://www.mikesdivestore.com/
A11: S07 | B11: Freediving | C11: Spearfishing UK | D11: UK competitor | E11: Specialist UK freediving/spearfishing category supply. | F11: High | G11: 46240 | H11: https://www.spearfishing.co.uk/freediving-gear/
A12: S08 | B12: Acoustics | C12: AcousticPanels.co.uk | D12: Supplier | E12: Explicit reseller/trade programme and trade pricing. | F12: High | G12: 46240 | H12: https://acousticpanels.co.uk/trade/
A13: S09 | B13: Acoustics | C13: GIK Acoustics | D13: Competitor | E13: Broad performance panel range and free room advice. | F13: High | G13: 46240 | H13: https://www.gikacoustics.net/en-gb/collections/acoustic-panels
A14: S10 | B14: Acoustics | C14: GIK Acoustics room kits | D14: Price benchmark | E14: Performance room kits start around £849 in the UK. | F14: High | G14: 46240 | H14: https://www.gikacoustics.net/en-gb/products/room-kits
A15: S11 | B15: Acoustics | C15: SilentSpace | D15: UK manufacturer | E15: Custom UK acoustic panel manufacturing and bespoke design. | F15: High | G15: 46240 | H15: https://silent-space.co.uk/
A16: S12 | B16: Acoustics | C16: The Wood Veneer Hub | D16: Compliance benchmark | E16: Fire-rated slat panels cite B-s1,d0 / BS EN 13501-1, demonstrating certification expectations. | F16: High | G16: 46240 | H16: https://www.thewoodveneerhub.co.uk/products/acupanel-fire-rated-acoustic-wood-wall-panel-samples
... A84: S80 | B84: Freeze dryers | C84: Harvest Right | D84: Manufacturer DTC | E84: Manufacturer advertises direct pricing and dealer/affiliate route—channel dependency risk. | F84: High | G84: 46240 | H84: https://harvestright.com/

Sheet Live SERP Cross-Check
A1: Live SERP Cross-Check (Sabroso) — every verdict from live Google UK page 1, August 2026
A2: Method: the partner's supplier-defensibility gate is correct and kept. What it needed was live page-1 evidence instead of desk-judged 'competition gap' scores. Verdict key: OCCUPIED = 3-4+ dedicated retail options on page 1 (pricing battle); CHANNEL CONFLICT = manufacturers/brands selling direct on page 1 (the pack's own hard stop); MIS-SERVED = Google substitutes services/info/wrong products because nobody sells the searched-for thing.
A4: Opportunity | B4: Partner decision | C4: Live page-1 verdict | D4: Channel conflict on page 1? | E4: Revised decision | F4: Evidence (live, deduped)
A5: Rainwater & drought-resilience systems | B5: Priority 1 (83, PASS) | C5: OCCUPIED — 5+ dedicated specialists with transactional pages | D5: YES — rainwaterharvesting.co.uk (manufacturer) at #1; Rainharvesting Systems also direct; Owls Hall supplies + installs | E5: REJECT under the pack's own hard stop | F5: rainwaterharvesting.co.uk, Owls Hall, Tanks Direct (£187-£4,291), Rainharvesting Systems, Celtic Sustainables, Direct Water Tanks (£342 kit), Sumps & Pumps (£4,761)
A6: Performance acoustic room kits | B6: Priority 2 (81.6, PASS) | C6: OCCUPIED — 'room kit' is a named category at 5+ sellers; every price tier covered (£57-£1,300) | D6: YES, SEVERE — the category is defined by manufacturers selling direct: GIK Acoustics #1 on both queries, Primacoustic, Skum, Advanced Acoustics, GB Foam. A reseller competes with its own suppliers everywhere | E6: REJECT — hardest channel conflict of the ten | F6: GIK (Room Kits £849), Polar/Primacoustic (£1,159), Skum (£254-894), Andertons category, Gear4music, Advanced Acoustics (£108-255), GB Foam (£57)
A7: Sensory-room packages | B7: Priority 3 (79.6, PASS) | C7: OCCUPIED — 8-10 dedicated specialists; fully transactional retail SERP with carted packages to £10.6k (not quote-led as assumed) | D7: YES — Experia (manufacturer) and TFH sell packages direct; Rhino UK sells design+install | E7: REJECT | F7: Sensory Direct (1.8k reviews), TTS (£2,098 bundle), SpaceKraft, Rhino UK, Experia, TFH (£5,427 package), Sensory Toy Warehouse (£280-£10,617), Sense Sensory (£6,995), SenTeq (£1,825)
A8: Separating & composting toilet systems | B8: Priority 4 (78.8, PASS) | C8: OCCUPIED — specialists and brand stores hold both SERPs incl. the campervan query | D8: YES, STRUCTURAL — five brands sell direct on page 1 (TROBOLO, Trelino, BOXIO, CompoCloset, NatSol) including the exact brands a reseller would stock; WooWoo is the incumbent multi-brand retailer | E8: REJECT | F8: WooWoo #1, TROBOLO, Trelino, BOXIO (£149.90), CompoCloset (Cuddy £870, #1 campervan), NatSol, Free Ranging Designs, LPG Shop
A9: Pond-health & filtration systems | B9: Supplier DD (75.8) | C9: OCCUPIED — 6-7 pond/koi specialists plus Amazon | D9: YES — Evolution Aqua (the premium koi filtration manufacturer, exactly the £850-3k bundle territory) ranks selling direct; Blagdon too | E9: REJECT | F9: All Pond Solutions (#1-2 + own Amazon store), Bradshaws, Absolute Koi, Evolution Aqua, World of Water, Swell, Pondkeeper, PowerBee, Blagdon
A10: Microcement installer systems | B10: Supplier DD (72.5) | C10: OCCUPIED — 8+ specialists/system brands; the 'restricted to trained installers' premise is false: brands sell DIY kits openly | D10: YES, SEVERE — 5 manufacturers sell direct on page 1 (Smartcret, Topciment, Festfloor, Epodex from £79.99, CARRcrete) | E10: REJECT | F10: Concrete Lab, Hawk & Trowel (#1 supplier), Smartcret, Relentless, Festfloor, Microcement Shop, MicrocementPro, Forcrete, CARRcrete, Topciment, Epodex, Stucco Veneziano + Amazon
A11: Golf simulator components & rooms | B11: Supplier DD (71.3) | C11: OCCUPIED (checked in our round 5) — 6+ UK specialists; GolfBays SimBox stocked by four retailers on page 1; Carl's Place import window closed | D11: Partial — GolfBays own-brand dominates via dealers | E11: REJECT (also flags conflict with the golfweights client relationship, as the pack itself noted) | F11: Inswing, Tekden, Golf Swing Systems, GolfBays, SimSpace, Huck Nets + four SimBox resellers
A12: Building diagnostic kits | B12: Supplier DD (70.3, ranked #10) | C12: MIS-SERVED at the bundle level — component damp-meter retail is occupied (4 dealers) but nobody owns the curated £1k-3.5k kit intent, and the thermal query is answered entirely by survey SERVICES, RICS PDFs and forums: Google serves 'get a survey done', not 'buy the kit' | D12: MILD, no hard stop — Protimeter ranks with content only, not selling; FLIR routes via dealers (Tester.co.uk). Dealer margin economics to check, not a page-1 conflict | E12: PROMOTE — the pack's only survivor. £300 ad test on kit terms + dealer-terms calls to FLIR/Protimeter channels before stock | F12: One Point Survey, PAM Ties, Toner Damp Proofing, York Survey (components); thermal query: RICS, Tester.co.uk advice content, five survey services, NHBC PDF, Reddit
A13: Cold-plunge & contrast therapy | B13: Supplier DD (66.5 watchlist) | C13: OCCUPIED — 8-10 dedicated UK sellers; the category IS brand-direct D2C now (£189-£15,750, core £849-£5,430); Amazon strong | D13: YES, STRUCTURAL — MyoMaster, LUMI, Polar Recovery, Brass Monkey, Kirami all own-brand and sell direct; no retail middle layer left | E13: REJECT — the pack's fad-risk caution was right; also KD 55 on 'cold plunge', the hardest keyword difficulty in this whole project | F13: LUMI, Kirami (£4,841+), Polar Recovery, MyoMaster (£849-950), Keico, Palm Spas, Concept Spa, Heavenly Hot Tubs, Eden Hut (£1,680), Outdoor Living, Celtic Timber (£885) + Amazon
A14: Premium freediving equipment | B14: No-go until supplier solved | C14: NO-GO CONFIRMED — five dedicated specialists holding seven organic slots (two hold doubles: the signature of an entrenched SERP) plus Decathlon, Amazon, eBay | D14: Partial — FreediverShop (Leaderfins' own channel) dominates premium shopping units | E14: NO-GO STANDS — the pack called this correctly | F14: Spearfishing UK (x2), Fins4U (x2), Start Point, Decathlon, Mike's Dive Store; carbon fins £125-270
A16: Reciprocal check: the partner's supplier gate applied to OUR current top three (from the executive report)
A17: Fire pit replacement bowls | C17: PASSES the supplier gate — metal spinners (Excell, Steel Spinnings, Tanfield) are trade fabricators with no D2C ambition or consumer channel; no conflict path visible.
A19: Natural swimming pond kits | C19: CONDITIONAL — Gordon Low sells liners direct to consumers, so the liner SKU alone has conflict risk. Differentiation must be the assembled kit (liner + filtration + plants + plan); get written terms on kit pricing before building.
A20: Garden putting green DIY kits | C20: CONDITIONAL — Nomow/Namgrass run consumer turf channels, so a raw-turf reseller would be undercut. Mitigation: own-brand kit SKU with a second turf source (TigerTurf), per the pack's ≥60% protected-revenue rule.
